ChengxuyuanRuheYouyaDeZhengLinghuaqian20/README.md
ChengxuyuanRuheYouyaDeZhengLinghuaqian20/__init__.py
ChengxuyuanRuheYouyaDeZhengLinghuaqian20/__main__.py
ChengxuyuanRuheYouyaDeZhengLinghuaqian20/file.epub
ChengxuyuanRuheYouyaDeZhengLinghuaqian20/index.html
ChengxuyuanRuheYouyaDeZhengLinghuaqian20/css/__init__.py
ChengxuyuanRuheYouyaDeZhengLinghuaqian20/css/annotations.css
ChengxuyuanRuheYouyaDeZhengLinghuaqian20/css/main.css
ChengxuyuanRuheYouyaDeZhengLinghuaqian20/css/normalize.css
ChengxuyuanRuheYouyaDeZhengLinghuaqian20/css/popup.css
ChengxuyuanRuheYouyaDeZhengLinghuaqian20/font/__init__.py
ChengxuyuanRuheYouyaDeZhengLinghuaqian20/font/fontello.eot
ChengxuyuanRuheYouyaDeZhengLinghuaqian20/font/fontello.svg
ChengxuyuanRuheYouyaDeZhengLinghuaqian20/font/fontello.ttf
ChengxuyuanRuheYouyaDeZhengLinghuaqian20/font/fontello.woff
ChengxuyuanRuheYouyaDeZhengLinghuaqian20/img/__init__.py
ChengxuyuanRuheYouyaDeZhengLinghuaqian20/img/annotator-glyph-sprite.png
ChengxuyuanRuheYouyaDeZhengLinghuaqian20/img/annotator-icon-sprite.png
ChengxuyuanRuheYouyaDeZhengLinghuaqian20/img/apple-touch-icon.png
ChengxuyuanRuheYouyaDeZhengLinghuaqian20/img/cancelfullscreen.png
ChengxuyuanRuheYouyaDeZhengLinghuaqian20/img/close.png
ChengxuyuanRuheYouyaDeZhengLinghuaqian20/img/fullscreen.png
ChengxuyuanRuheYouyaDeZhengLinghuaqian20/img/loader.gif
ChengxuyuanRuheYouyaDeZhengLinghuaqian20/img/menu-icon.png
ChengxuyuanRuheYouyaDeZhengLinghuaqian20/img/save.png
ChengxuyuanRuheYouyaDeZhengLinghuaqian20/img/saved.png
ChengxuyuanRuheYouyaDeZhengLinghuaqian20/img/settings-s.png
ChengxuyuanRuheYouyaDeZhengLinghuaqian20/img/settings.png
ChengxuyuanRuheYouyaDeZhengLinghuaqian20/img/star.png
ChengxuyuanRuheYouyaDeZhengLinghuaqian20/js/__init__.py
ChengxuyuanRuheYouyaDeZhengLinghuaqian20/js/epub.js
ChengxuyuanRuheYouyaDeZhengLinghuaqian20/js/epub.min.js
ChengxuyuanRuheYouyaDeZhengLinghuaqian20/js/epub.min.map
ChengxuyuanRuheYouyaDeZhengLinghuaqian20/js/hooks.min.js
chengxuyuan_ruhe_youya_de_zheng_linghuaqian_2_0-2024.3.5.0.dist-info/METADATA
chengxuyuan_ruhe_youya_de_zheng_linghuaqian_2_0-2024.3.5.0.dist-info/WHEEL
chengxuyuan_ruhe_youya_de_zheng_linghuaqian_2_0-2024.3.5.0.dist-info/entry_points.txt
chengxuyuan_ruhe_youya_de_zheng_linghuaqian_2_0-2024.3.5.0.dist-info/top_level.txt
chengxuyuan_ruhe_youya_de_zheng_linghuaqian_2_0-2024.3.5.0.dist-info/RECORD
